xqdata/__init__.py
xqdata/dataapi.py
xqdata/mock/__init__.py
xqdata/rq/__init__.py
xqdata/rq/api.py
xqdata/rq/config.py
xqdata/rq/func_factor.py
xqdata/rq/func_info.py
xqdata/rq/utils.py
xqdata-0.2.4.dist-info/WHEEL
xqdata-0.2.4.dist-info/entry_points.txt
xqdata-0.2.4.dist-info/METADATA
xqdata-0.2.4.dist-info/RECORD
