Metadata-Version: 2.3
Name: xqdata
Version: 0.2.4
Summary: 统一适配rqdata/火富牛API等数据源
Author: xuanq
Author-email: xuanq <xuanqiraphael@gmail.com>
Requires-Dist: pandas>=2.3.3
Requires-Dist: rqdatac>=3.3.2 ; extra == 'rq'
Requires-Python: >=3.10
Provides-Extra: rq
